{"chunk_definitions":[{"row":63,"row_count":1,"visible":true,"expansion_state":0,"options":{"engine":"r","label":"unnamed-chunk-50"},"document_id":"CC8E8BC5","chunk_id":"cxktp27pqfddt","chunk_label":"unnamed-chunk-1"},{"row":93,"row_count":1,"visible":true,"expansion_state":0,"options":{"engine":"r","label":"unnamed-chunk-59"},"document_id":"CC8E8BC5","chunk_id":"cxady56l7cmzj","chunk_label":"unnamed-chunk-2"},{"row":114,"row_count":1,"visible":true,"expansion_state":0,"options":{"engine":"r","label":"unnamed-chunk-63"},"document_id":"CC8E8BC5","chunk_id":"cqwrwjtabx68t","chunk_label":"unnamed-chunk-3"}],"doc_write_time":1630787651,"working_dir":null,"default_chunk_options":{}}